valr_python/__init__.py
valr_python/decorators.py
valr_python/enum.py
valr_python/exceptions.py
valr_python/rest_base.py
valr_python/rest_client.py
valr_python/utils.py
valr_python/ws_client.py
valr_python-0.2.7.dist-info/AUTHORS.rst
valr_python-0.2.7.dist-info/LICENSE
valr_python-0.2.7.dist-info/METADATA
valr_python-0.2.7.dist-info/WHEEL
valr_python-0.2.7.dist-info/top_level.txt
valr_python-0.2.7.dist-info/RECORD
