Metadata-Version: 2.1
Name: valr-python
Version: 0.2.7
Summary: Python SDK for the VALR REST API
Home-page: https://github.com/jonathanelscpt/valr-python
Author: Jonathan Els
Author-email: jonathanelscpt@gmail.com
License: MIT
Project-URL: Changelog, https://github.com/jonathanelscpt/valr-python/blob/master/CHANGELOG.rst
Project-URL: Issue Tracker, https://github.com/jonathanelscpt/valr-python/issues
Keywords: VALR,REST,API,Bitcoin,Ethereum,stream,websocket
Platform: UNKNOWN
Classifier: Development Status :: 3 - Alpha
Classifier: Intended Audience :: Developers
Classifier: License :: OSI Approved :: MIT License
Classifier: Operating System :: Unix
Classifier: Programming Language :: Python
Classifier: Programming Language :: Python :: 3
Classifier: Programming Language :: Python :: 3 :: Only
Classifier: Programming Language :: Python :: 3.6
Classifier: Programming Language :: Python :: 3.7
Classifier: Programming Language :: Python :: 3.8
Classifier: Programming Language :: Python :: Implementation :: CPython
Classifier: Programming Language :: Python :: Implementation :: PyPy
Classifier: Topic :: Utilities
Requires-Python: >=3.6
License-File: LICENSE
License-File: AUTHORS.rst
Requires-Dist: requests
Requires-Dist: websockets
Requires-Dist: asyncio
Requires-Dist: simplejson
